meteoalarm/__init__.py
meteoalarm/meteoalarm.py
meteoalarm/assets/MeteoAlarm_urls.yaml
meteoalarm/assets/geocodes.json
meteoalarm-0.1.2.dist-info/LICENSE
meteoalarm-0.1.2.dist-info/METADATA
meteoalarm-0.1.2.dist-info/WHEEL
meteoalarm-0.1.2.dist-info/top_level.txt
meteoalarm-0.1.2.dist-info/RECORD
