Metadata-Version: 2.2
Name: meteoalarm
Version: 0.1.2
Summary: A Python library for accessing MeteoAlarm weather warnings
Author-email: Niklas Jordan <hello@niklasjordan.com>
License: Unless otherwise specified, the contents of this repository are distributed 
Project-URL: Homepage, https://github.com/NiklasJordan/meteoalarm
Classifier: Programming Language :: Python :: 3
Classifier: License :: OSI Approved :: MIT License
Classifier: Operating System :: OS Independent
License-File: LICENSE
Requires-Dist: requests>=2.25.0
Requires-Dist: pyyaml>=5.1
Requires-Dist: pytz>=2021.1
